model_training_api/model_training_api.py
aissemble_foundation_model_training_api-2.0.0.dist-info/LICENSE
aissemble_foundation_model_training_api-2.0.0.dist-info/LICENSE.txt
aissemble_foundation_model_training_api-2.0.0.dist-info/METADATA
aissemble_foundation_model_training_api-2.0.0.dist-info/WHEEL
aissemble_foundation_model_training_api-2.0.0.dist-info/RECORD
